Ejercicio5/Rom.v
module Rom_2 (input [6:0] entry, output [12:0] out);
  reg [12:0] out;
  always @ (*) begin
    casez (entry)
      7'b??????0: out = 13'b1000000001000;
      7'b00001?1: out = 13'b0100000001000;
      7'b00000?1: out = 13'b1000000001000;
      7'b00011?1: out = 13'b1000000001000;
      7'b00010?1: out = 13'b0100000001000;
      7'b0010??1: out = 13'b0001001000010;
      7'b0011??1: out = 13'b1001001100000;
      7'b0100??1: out = 13'b0011010000010;
      7'b0101??1: out = 13'b0011010000100;
      7'b0110??1: out = 13'b1011010100000;
      7'b0111??1: out = 13'b1000000111000;
      7'b1000?11: out = 13'b0100000001000;
      7'b1000?01: out = 13'b1000000001000;
      7'b1001?11: out = 13'b1000000001000;
      7'b1001?01: out = 13'b0100000001000;
      7'b1010??1: out = 13'b0011011000010;
      7'b1011??1: out = 13'b1011011100000;
      7'b1100??1: out = 13'b0100000001000;
      7'b1101??1: out = 13'b0000000001001;
      7'b1110??1: out = 13'b0011100000010;
      7'b1111??1: out = 13'b1011100100000;
      default: out = 13'b0000000000000;
    endcase
  end
endmodule

Ejercicio5/Rom_tb.v
module testb ();
  reg [6:0] entry; wire [12:0] out;
  Rom_2 Rom_2 (entry, out);
  initial begin
    $display("\t\tTime \ten6 \ten5 \ten4 \ten3 \ten2 \ten1 \ten0 \tout");
    $monitor ("%d\t %b\t %b\t %b\t %b\t %b\t %b\t%b\t %b\t", $time, entry[6], entry[5], entry[4], entry[3], entry[2], entry[1], entry[0], out);
    entry[6]= 1'bx; entry[5]= 1'bx; entry[4]= 1'bx; entry[3]= 1'bx; entry[2]= 1'bx; entry[1]= 1'bx; entry[0]= 0;
    #10 entry[6]= 0; entry[5]= 0; entry[4]= 0; entry[3]= 0; entry[2]= 1; entry[1]= 1'bx; entry[0]= 1;
    #10 entry[6]= 0; entry[5]= 0; entry[4]= 0; entry[3]= 0; entry[2]= 0; entry[1]= 1'bx; entry[0]= 1;
    #10 entry[6]= 0; entry[5]= 0; entry[4]= 0; entry[3]= 1; entry[2]= 1; entry[1]= 1'bx; entry[0]= 1;
    #10 entry[6]= 0; entry[5]= 0; entry[4]= 0; entry[3]= 1; entry[2]= 0; entry[1]= 1'bx; entry[0]= 1;
    #10 entry[6]= 0; entry[5]= 0; entry[4]= 1; entry[3]= 0; entry[2]= 1'bx; entry[1]= 1'bx; entry[0]= 1;
    #10 entry[6]= 0; entry[5]= 0; entry[4]= 1; entry[3]= 1; entry[2]= 1'bx; entry[1]= 1'bx; entry[0]= 1;
    #10 entry[6]= 0; entry[5]= 0; entry[4]= 0; entry[3]= 0; entry[2]= 0; entry[1]= 1'bx; entry[0]= 1;
    #10 entry[6]= 0; entry[5]= 1; entry[4]= 0; entry[3]= 1; entry[2]= 1'bx; entry[1]= 1'bx; entry[0]= 1;
    #10 entry[6]= 0; entry[5]= 1; entry[4]= 1; entry[3]= 0; entry[2]= 1'bx; entry[1]= 1'bx; entry[0]= 1;
    #10 entry[6]= 0; entry[5]= 1; entry[4]= 1; entry[3]= 1; entry[2]= 1'bx; entry[1]= 1'bx; entry[0]= 1;
    #10 entry[6]= 0; entry[5]= 0; entry[4]= 0; entry[3]= 0; entry[2]= 0; entry[1]= 1'bx; entry[0]= 1;
    #10 entry[6]= 1; entry[5]= 0; entry[4]= 0; entry[3]= 0; entry[2]= 1'bx; entry[1]= 1; entry[0]= 1;
    #10 entry[6]= 0; entry[5]= 0; entry[4]= 0; entry[3]= 0; entry[2]= 0; entry[1]= 1'bx; entry[0]= 1;
    #10 entry[6]= 1; entry[5]= 0; entry[4]= 0; entry[3]= 0; entry[2]= 1'bx; entry[1]= 0; entry[0]= 1;
    #10 entry[6]= 1; entry[5]= 0; entry[4]= 0; entry[3]= 1; entry[2]= 1'bx; entry[1]= 1; entry[0]= 1;
    #10 entry[6]= 1; entry[5]= 0; entry[4]= 0; entry[3]= 1; entry[2]= 1'bx; entry[1]= 0; entry[0]= 1;
    #10 entry[6]= 1; entry[5]= 0; entry[4]= 1; entry[3]= 0; entry[2]= 1'bx; entry[1]= 1'bx; entry[0]= 1;
    #10 entry[6]= 1; entry[5]= 0; entry[4]= 1; entry[3]= 1; entry[2]= 1'bx; entry[1]= 1'bx; entry[0]= 1;
    #10 entry[6]= 1; entry[5]= 1; entry[4]= 0; entry[3]= 0; entry[2]= 1'bx; entry[1]= 1'bx; entry[0]= 1;
    #10 entry[6]= 1; entry[5]= 1; entry[4]= 0; entry[3]= 1; entry[2]= 1'bx; entry[1]= 1'bx; entry[0]= 1;
    #10 entry[6]= 1; entry[5]= 1; entry[4]= 1; entry[3]= 0; entry[2]= 1'bx; entry[1]= 1'bx; entry[0]= 1;
    #10 entry[6]= 1; entry[5]= 1; entry[4]= 1; entry[3]= 1; entry[2]= 1'bx; entry[1]= 1'bx; entry[0]= 1;
    #10 entry[6]= 1; entry[5]= 1; entry[4]= 1; entry[3]= 1; entry[2]= 0; entry[1]= 1; entry[0]= 1;
    #10 entry[6]= 1; entry[5]= 1; entry[4]= 1; entry[3]= 1; entry[2]= 0; entry[1]= 0; entry[0]= 0;
    #10 entry[6]= 1; entry[5]= 1; entry[4]= 1; entry[3]= 1; entry[2]= 1; entry[1]= 1; entry[0]= 1;
    #10 entry[6]= 1; entry[5]= 1; entry[4]= 1; entry[3]= 0; entry[2]= 0; entry[1]= 1; entry[0]= 0;
    #10 entry[6]= 0; entry[5]= 0; entry[4]= 1; entry[3]= 1; entry[2]= 0; entry[1]= 1; entry[0]= 1;
    #10 $finish;
  end
  initial begin
    $dumpfile("Rom_tb.vcd");
    $dumpvars(0,testb);
  end
endmodule

Ejercicio5/Rom_tb.vcd
$date
	Sat Oct 31 09:53:53 2020
$end
$version
	Icarus Verilog
$end
$timescale
	1ps
$end
$scope module testb $end
$var wire 13 ! out [12:0] $end
$var reg 7 " entry [6:0] $end
$scope module Rom_2 $end
$var wire 7 # entry [6:0] $end
$var reg 13 $ out [12:0] $end
$upscope $end
$upscope $end
$enddefinitions $end
#0
$dumpvars
b1000000001000 $
bx0 #
bx0 "
b1000000001000 !
$end
#10
b100000001000 !
b100000001000 $
b1x1 "
b1x1 #
#20
b1000000001000 !
b1000000001000 $
b0x1 "
b0x1 #
#30
b11x1 "
b11x1 #
#40
b100000001000 !
b100000001000 $
b10x1 "
b10x1 #
#50
b1001000010 !
b1001000010 $
b10xx1 "
b10xx1 #
#60
b1001001100000 !
b1001001100000 $
b11xx1 "
b11xx1 #
#70
b1000000001000 !
b1000000001000 $
b0x1 "
b0x1 #
#80
b11010000100 !
b11010000100 $
b101xx1 "
b101xx1 #
#90
b1011010100000 !
b1011010100000 $
b110xx1 "
b110xx1 #
#100
b1000000111000 !
b1000000111000 $
b111xx1 "
b111xx1 #
#110
b1000000001000 !
b1000000001000 $
b0x1 "
b0x1 #
#120
b100000001000 !
b100000001000 $
b1000x11 "
b1000x11 #
#130
b1000000001000 !
b1000000001000 $
b0x1 "
b0x1 #
#140
b1000x01 "
b1000x01 #
#150
b1001x11 "
b1001x11 #
#160
b100000001000 !
b100000001000 $
b1001x01 "
b1001x01 #
#170
b11011000010 !
b11011000010 $
b1010xx1 "
b1010xx1 #
#180
b1011011100000 !
b1011011100000 $
b1011xx1 "
b1011xx1 #
#190
b100000001000 !
b100000001000 $
b1100xx1 "
b1100xx1 #
#200
b1001 !
b1001 $
b1101xx1 "
b1101xx1 #
#210
b11100000010 !
b11100000010 $
b1110xx1 "
b1110xx1 #
#220
b1011100100000 !
b1011100100000 $
b1111xx1 "
b1111xx1 #
#230
b1111011 "
b1111011 #
#240
b1000000001000 !
b1000000001000 $
b1111000 "
b1111000 #
#250
b1011100100000 !
b1011100100000 $
b1111111 "
b1111111 #
#260
b1000000001000 !
b1000000001000 $
b1110010 "
b1110010 #
#270
b1001001100000 !
b1001001100000 $
b11011 "
b11011 #
